mlpype/spark/__init__.py
mlpype/spark/data/__init__.py
mlpype/spark/data/spark_data_frame_source.py
mlpype/spark/data/spark_read.py
mlpype/spark/data/spark_sql_source.py
mlpype/spark/evaluate/__init__.py
mlpype/spark/evaluate/spark_evaluator.py
mlpype/spark/model/__init__.py
mlpype/spark/model/linear_spark_model.py
mlpype/spark/model/spark_model.py
mlpype/spark/model/types.py
mlpype/spark/pipeline/__init__.py
mlpype/spark/pipeline/spark_pipe.py
mlpype/spark/pipeline/spark_type_checker.py
mlpype/spark/serialiser/__init__.py
mlpype/spark/serialiser/spark_serialiser.py
mlpype/spark/utils/__init__.py
mlpype/spark/utils/guarantee.py
mlpype_spark-0.6.12.dist-info/METADATA
mlpype_spark-0.6.12.dist-info/WHEEL
mlpype_spark-0.6.12.dist-info/RECORD
