Metadata-Version: 2.4
Name: mlpype-spark
Version: 0.6.12
Summary: Spark extension for MLpype
Author: Jeroen van den Hoven
License: MIT
Requires-Python: >=3.9
Requires-Dist: mlpype-base
Requires-Dist: pyspark>=3.4.0
Provides-Extra: strict
Requires-Dist: pyspark==3.4.0; extra == 'strict'
